CHANGELOG.md
MANIFEST.in
README.rst
setup.cfg
setup.py
redisengine/__init__.py
redisengine/__init__.pyc
redisengine/connection.py
redisengine/connection.pyc
redisengine/exceptions.py
redisengine/exceptions.pyc
redisengine/fields.py
redisengine/fields.pyc
redisengine/utils.py
redisengine/utils.pyc
redisengine.egg-info/PKG-INFO
redisengine.egg-info/SOURCES.txt
redisengine.egg-info/dependency_links.txt
redisengine.egg-info/requires.txt
redisengine.egg-info/top_level.txt
redisengine/core/__init__.py
redisengine/core/__init__.pyc
redisengine/core/common.py
redisengine/core/common.pyc
redisengine/core/fields.py
redisengine/core/fields.pyc
redisengine/core/manager.py
redisengine/core/manager.pyc
redisengine/core/tree_base.py
redisengine/core/tree_base.pyc
redisengine/core/utils.py
redisengine/direct/__init__.py
redisengine/direct/__init__.pyc
redisengine/direct/operators.py
redisengine/direct/operators.pyc
redisengine/direct/tree.py
redisengine/direct/tree.pyc
redisengine/direct/base/__init__.py
redisengine/direct/base/__init__.pyc
redisengine/direct/base/metaclasses.py
redisengine/direct/base/metaclasses.pyc
redisengine/direct/base/operators.py
redisengine/direct/base/operators.pyc
redisengine/proxy/__init__.py
redisengine/proxy/__init__.pyc
redisengine/proxy/operators.py
redisengine/proxy/operators.pyc
redisengine/proxy/tree.py
redisengine/proxy/tree.pyc
redisengine/proxy/base/__init__.py
redisengine/proxy/base/__init__.pyc
redisengine/proxy/base/metaclasses.py
redisengine/proxy/base/metaclasses.pyc
redisengine/proxy/base/operators.py
redisengine/proxy/base/operators.pyc
redisengine/proxy/base/tree.py
redisengine/proxy/base/tree.pyc
tests/__init__.py
tests/__init__.pyc
tests/test_connection.py
tests/test_connection.pyc
tests/fields/__init__.py
tests/fields/__init__.pyc
tests/fields/test_fields.py
tests/fields/test_fields.pyc
tests/trees/__init__.py
tests/trees/__init__.pyc
tests/trees/test_direct_tree.py
tests/trees/test_direct_tree.pyc
tests/trees/test_proxy_class_methods.py
tests/trees/test_proxy_class_methods.pyc
tests/trees/test_proxy_delta.py
tests/trees/test_proxy_delta.pyc
tests/trees/test_proxy_queryset.py
