Metadata-Version: 1.1
Name: redisengine
Version: 0.1.1
Summary: A MongoEngine-inspired, Object-Type mapper for working with Redis
Home-page: https://github.com/RedisEngine/redisengine
Author: Kris Kavalieri
Author-email: kris.kavalieri@gmail.com
License: MIT
Download-URL: https://github.com/RedisEngine/redisengine/tarball/master
Platform: any
Classifier: Intended Audience :: Developers
Classifier: Topic :: Database
Classifier: Topic :: Software Development :: Libraries :: Python Modules
